setup.py
dhruv_distributions.egg-info/PKG-INFO
dhruv_distributions.egg-info/SOURCES.txt
dhruv_distributions.egg-info/dependency_links.txt
dhruv_distributions.egg-info/not-zip-safe
dhruv_distributions.egg-info/top_level.txt
distributions/Binomialdistribution.py
distributions/Gaussiandistribution.py
distributions/Generaldistribution.py
distributions/__init__.py